{"className":"Sprite","hitboxes":[{"className":"Hitbox","tags":"","width":13,"height":13,"offset":{"className":"Point","x":0,"y":0},"rect":{"className":"Rect","topLeftPoint":{"className":"Point","x":343.5,"y":293.5},"botRightPoint":{"className":"Point","x":356.5,"y":306.5}},"isTrigger":true}],"frames":[{"className":"Frame","rect":{"className":"Rect","topLeftPoint":{"className":"Point","x":368,"y":958},"botRightPoint":{"className":"Point","x":381,"y":971}},"duration":0.066,"offset":{"className":"Point","x":0,"y":0},"hitboxes":[],"POIs":[]}],"POIs":[],"name":"shotgun_ice","path":"assets/sprites/shotgun_ice.json","alignment":"center","wrapMode":"once","spritesheetPath":"assets/spritesheets/effects.png"}