{"className":"Sprite","hitboxes":[],"frames":[{"className":"Frame","rect":{"className":"Rect","topLeftPoint":{"className":"Point","x":394,"y":371},"botRightPoint":{"className":"Point","x":433,"y":416}},"duration":0.066,"offset":{"className":"Point","x":0,"y":0},"hitboxes":[],"POIs":[]},{"className":"Frame","rect":{"className":"Rect","topLeftPoint":{"className":"Point","x":435,"y":371},"botRightPoint":{"className":"Point","x":474,"y":416}},"duration":0.066,"offset":{"className":"Point","x":0,"y":0},"hitboxes":[],"POIs":[]},{"className":"Frame","rect":{"className":"Rect","topLeftPoint":{"className":"Point","x":480,"y":370},"botRightPoint":{"className":"Point","x":518,"y":416}},"duration":0.066,"offset":{"className":"Point","x":0,"y":0},"hitboxes":[],"POIs":[]}],"POIs":[],"name":"zero_die","path":"assets/sprites/zero_die.json","alignment":"botmid","wrapMode":"once","spritesheetPath":"assets/spritesheets/zero.png"}